{
  "trace_id": "20260527_171002",
  "query": "현대자동차 전기차 전망 분석",
  "persona": "growth_investor",
  "ticker": "005930",
  "started_at": "2026-05-27 17:10:02",
  "completed_at": "2026-05-27 17:10:11",
  "steps": [
    {
      "step": "retrieval",
      "status": "ok",
      "summary": "chunks=5",
      "timestamp": "2026-05-27 17:10:02"
    },
    {
      "step": "context_assembly",
      "status": "ok",
      "summary": "len=3388",
      "timestamp": "2026-05-27 17:10:02"
    },
    {
      "step": "unified_context",
      "status": "ok",
      "summary": "len=5610",
      "timestamp": "2026-05-27 17:10:02"
    },
    {
      "step": "character_analysis",
      "status": "ok",
      "summary": "bullish=2",
      "timestamp": "2026-05-27 17:10:07"
    },
    {
      "step": "evaluation",
      "status": "ok",
      "summary": "hallucination=low",
      "timestamp": "2026-05-27 17:10:07"
    },
    {
      "step": "reflection",
      "status": "ok",
      "summary": "분석은 현대자동차의 전기차 부문에 대한 긍정적인 전망을 제시하고 있으나, 하락 요인과 리스",
      "timestamp": "2026-05-27 17:10:11"
    },
    {
      "step": "memory_save",
      "status": "ok",
      "summary": "layer=short_term",
      "timestamp": "2026-05-27 17:10:11"
    },
    {
      "step": "importance_update",
      "status": "ok",
      "summary": "score=1.00",
      "timestamp": "2026-05-27 17:10:11"
    },
    {
      "step": "temporal_tracking",
      "status": "ok",
      "summary": "action=promote",
      "timestamp": "2026-05-27 17:10:11"
    },
    {
      "step": "event_graph",
      "status": "ok",
      "summary": "nodes=22 rels=64",
      "timestamp": "2026-05-27 17:10:11"
    },
    {
      "step": "stock_chain",
      "status": "ok",
      "summary": "links=75",
      "timestamp": "2026-05-27 17:10:11"
    }
  ],
  "retrieval_summary": {
    "chunk_count": 5,
    "max_score": 0.280991
  },
  "reflection_summary": "분석은 현대자동차의 전기차 부문에 대한 긍정적인 전망을 제시하고 있으나, 하락 요인과 리스크가 충분히 반영되지 않아 균형이 부족합니다. 특히, 글로벌 경쟁과 내부 리스크 외에도 추가적인 리스크 요소가 누락되어 있습니다.",
  "temporal_action": "promote",
  "stock_chain_links": 0
}